LICENSE
MANIFEST.in
README.rst
setup.py
cheesepi/LICENSE.txt
cheesepi/VERSION
cheesepi/__init__.py
cheesepi/cheesepi.conf
cheesepi/cheesepi.default.conf
cheesepi/config.py
cheesepi/dispatcher.py
cheesepi/exceptions.py
cheesepi/schedule.dat
cheesepi/schedule.default.dat
cheesepi/tmp
cheesepi/utils.py
cheesepi.egg-info/PKG-INFO
cheesepi.egg-info/SOURCES.txt
cheesepi.egg-info/dependency_links.txt
cheesepi.egg-info/entry_points.txt
cheesepi.egg-info/not-zip-safe
cheesepi.egg-info/requires.txt
cheesepi.egg-info/top_level.txt
cheesepi/bin/.DS_Store
cheesepi/bin/__init__.py
cheesepi/bin/cheesepi.service
cheesepi/bin/cheesepi.sh
cheesepi/bin/run_task.py
cheesepi/bin/newdash/bootstrap.min.css
cheesepi/bin/newdash/bootstrap.min.js
cheesepi/bin/newdash/d3.min.js
cheesepi/bin/newdash/dashboard.html
cheesepi/bin/newdash/data.json
cheesepi/bin/newdash/donor.html
cheesepi/bin/newdash/gchart.html
cheesepi/bin/newdash/gchart2.html
cheesepi/bin/newdash/jquery-1.12.0.min.js
cheesepi/bin/newdash/jquery-2.2.0.min.js
cheesepi/bin/newdash/line.html
cheesepi/bin/tools/iperf3-arm
cheesepi/bin/tools/influxdb/benchmark_config.toml
cheesepi/bin/tools/influxdb/config.toml
cheesepi/bin/tools/influxdb/influxdb-benchmark.arm
cheesepi/bin/tools/influxdb/influxdb.arm
cheesepi/bin/tools/influxdb/admin/index.html
cheesepi/bin/tools/influxdb/admin/fonts/font-mfizz.eot
cheesepi/bin/tools/influxdb/admin/fonts/font-mfizz.svg
cheesepi/bin/tools/influxdb/admin/fonts/font-mfizz.ttf
cheesepi/bin/tools/influxdb/admin/fonts/font-mfizz.woff
cheesepi/bin/tools/influxdb/admin/help/queries.html
cheesepi/bin/tools/influxdb/admin/images/favicon.ico
cheesepi/bin/tools/influxdb/admin/images/influxdb-light-24px.png
cheesepi/bin/tools/influxdb/admin/interfaces/default/index.html
cheesepi/bin/tools/influxdb/admin/javascripts/admin.js
cheesepi/bin/tools/influxdb/admin/javascripts/all.js
cheesepi/bin/tools/influxdb/admin/javascripts/interfaces/default.js
cheesepi/bin/tools/influxdb/admin/javascripts/vendor/angular-cookies.js
cheesepi/bin/tools/influxdb/admin/javascripts/vendor/angular.js
cheesepi/bin/tools/influxdb/admin/javascripts/vendor/custom.modernizr.js
cheesepi/bin/tools/influxdb/admin/javascripts/vendor/foundation.min.js
