Metadata-Version: 1.1
Name: cheesepi
Version: 1.9.21
Summary: CheesePi Library
Home-page: http://cheesepi.sics.se
Author: Liam McNamara
Author-email: liamjjmcnamara@sics.se
License: UNKNOWN
Platform: RaspberryPi
Classifier: Development Status :: 4 - Beta
Classifier: Operating System :: POSIX
Classifier: Programming Language :: Python :: 2
Classifier: Programming Language :: Python :: 2.7
Classifier: Topic :: Internet
Classifier: Topic :: System :: Logging
